text_info-1.0.4.dist-info/licenses/LICENSE
ti/__init__.py
ti/cheatsheet.py
ti/parameters.py
ti/cli/__init__.py
ti/cli/generate_manifests.py
ti/cli/validate_tei.py
ti/info/helpers.py
ti/info/iiif.py
ti/info/scans.py
ti/info/tei.py
ti/info/fof/filenotfound.gif
ti/info/fof/filenotfound.jpf
ti/info/fof/filenotfound.jpg
ti/info/fof/filenotfound.pdf
ti/info/fof/filenotfound.png
ti/info/fof/filenotfound.tiff
ti/kit/__init__.py
ti/kit/command.py
ti/kit/files.py
ti/kit/generic.py
ti/kit/helpers.py
ti/kit/pdocs.py
ti/kit/repo.py
ti/kit/timestamp.py
ti/tools/helpers.py
ti/tools/xmlschema.py
ti/tools/jing/copying.html
ti/tools/jing/isorelax.copying.txt
ti/tools/jing/isorelax.jar
ti/tools/jing/jing-ant.html
ti/tools/jing/jing-datatypes.html
ti/tools/jing/jing-other.html
ti/tools/jing/jing.html
ti/tools/jing/jing.jar
ti/tools/jing/nrl.html
ti/tools/jing/pluggable-datatypes.html
ti/tools/jing/saxon.jar
ti/tools/jing/xerces.copying.txt
ti/tools/jing/xercesImpl.jar
ti/tools/jing/xml-apis.jar
ti/tools/tei/tei_all.rng
ti/tools/tei/tei_all.xsd
ti/tools/tei/teix.xsd
ti/tools/tei/xml.xsd
ti/tools/trang/copying.txt
ti/tools/trang/trang-manual.html
ti/tools/trang/trang.jar
text_info-1.0.4.dist-info/METADATA
text_info-1.0.4.dist-info/WHEEL
text_info-1.0.4.dist-info/entry_points.txt
text_info-1.0.4.dist-info/top_level.txt
text_info-1.0.4.dist-info/RECORD
